brevo/__init__.py
brevo_api-1.2.0.dist-info/licenses/LICENSE
brevo_api-1.2.0.dist-info/METADATA
brevo_api-1.2.0.dist-info/WHEEL
brevo_api-1.2.0.dist-info/top_level.txt
brevo_api-1.2.0.dist-info/RECORD
