Metadata-Version: 2.4
Name: brevo-api
Version: 1.2.0
Summary: Python API Client for Brevo
Project-URL: Homepage, http://github.com/ChemicalLuck/brevo-api-python
Classifier: Development Status :: 3 - Alpha
Classifier: Intended Audience :: Information Technology
Classifier: License :: OSI Approved :: MIT License
Classifier: Natural Language :: English
Classifier: Programming Language :: Python :: 3
Classifier: Topic :: Software Development :: Libraries :: Python Modules
Classifier: Topic :: Software Development :: Testing
Classifier: Topic :: Utilities
Requires-Python: >=3.8
License-File: LICENSE
Requires-Dist: brevo-python==1.2.0
Dynamic: license-file
